dispenser/__init__.py
dispenser/create.py
dispenser/update.py
dispenser/version_base.py
dispenser/impl/__init__.py
dispenser/impl/forge.py
dispenser/impl/paper.py
dispenser/impl/vanilla.py
dispenser-0.3.0.dist-info/METADATA
dispenser-0.3.0.dist-info/WHEEL
dispenser-0.3.0.dist-info/top_level.txt
dispenser-0.3.0.dist-info/RECORD
