Metadata-Version: 2.1
Name: dispenser
Version: 0.3.0
Summary: Create Minecraft Servers of various types
Home-page: https://github.com/xImAnton/dispenser
Author: xImAnton_
Author-email: admin@ximanton.de
Project-URL: Bug Tracker, https://github.com/xImAnton/dispenser/issues
Classifier: Programming Language :: Python :: 3
Classifier: Operating System :: OS Independent
Classifier: License :: OSI Approved :: GNU General Public License v3 (GPLv3)
Requires-Python: >=3.9
